[
  {
    "name": "01",
    "path": "01",
    "thumb": "Thumb.jpg",
    "date": ""
  },
  {
    "name": "02",
    "path": "02",
    "thumb": "Thumb.jpg",
    "date": ""
  },
  {
    "name": "027",
    "path": "027",
    "thumb": "Thumb.jpg",
    "date": ""
  },
  {
    "name": "028",
    "path": "028",
    "thumb": "Thumb.jpg",
    "date": ""
  },
  {
    "name": "029",
    "path": "029",
    "thumb": "Thumb.jpg",
    "date": ""
  },
  {
    "name": "03",
    "path": "03",
    "thumb": "Thumb.jpg",
    "date": ""
  },
  {
    "name": "030",
    "path": "030",
    "thumb": "Thumb.jpg",
    "date": ""
  },
  {
    "name": "031",
    "path": "031",
    "thumb": "Thumb.jpg",
    "date": ""
  },
  {
    "name": "032",
    "path": "032",
    "thumb": "Thumb.jpg",
    "date": ""
  },
  {
    "name": "033",
    "path": "033",
    "thumb": "Thumb.jpg",
    "date": ""
  },
  {
    "name": "034",
    "path": "034",
    "thumb": "Thumb.jpg",
    "date": ""
  },
  {
    "name": "035",
    "path": "035",
    "thumb": "Thumb.jpg",
    "date": ""
  },
  {
    "name": "036",
    "path": "036",
    "thumb": "Thumb.jpg",
    "date": ""
  },
  {
    "name": "037",
    "path": "037",
    "thumb": "Thumb.jpg",
    "date": ""
  },
  {
    "name": "038",
    "path": "038",
    "thumb": "Thumb.jpg",
    "date": ""
  },
  {
    "name": "039",
    "path": "039",
    "thumb": "Thumb.jpg",
    "date": ""
  },
  {
    "name": "04",
    "path": "04",
    "thumb": "Thumb.jpg",
    "date": ""
  },
  {
    "name": "040",
    "path": "040",
    "thumb": "Thumb.jpg",
    "date": ""
  },
  {
    "name": "041",
    "path": "041",
    "thumb": "Thumb.jpg",
    "date": ""
  },
  {
    "name": "05",
    "path": "05",
    "thumb": "Thumb.jpg",
    "date": ""
  },
  {
    "name": "06",
    "path": "06",
    "thumb": "Thumb.jpg",
    "date": ""
  },
  {
    "name": "07",
    "path": "07",
    "thumb": "Thumb.jpg",
    "date": ""
  },
  {
    "name": "08",
    "path": "08",
    "thumb": "Thumb.jpg",
    "date": ""
  },
  {
    "name": "09",
    "path": "09",
    "thumb": "Thumb.jpg",
    "date": ""
  },
  {
    "name": "10",
    "path": "10",
    "thumb": "Thumb.jpg",
    "date": ""
  },
  {
    "name": "11",
    "path": "11",
    "thumb": "Thumb.jpg",
    "date": ""
  },
  {
    "name": "12",
    "path": "12",
    "thumb": "Thumb.jpg",
    "date": ""
  },
  {
    "name": "13",
    "path": "13",
    "thumb": "Thumb.jpg",
    "date": ""
  }
]